neo3vm.cpython-39-darwin.so
neo3vm-0.10.1.dist-info/METADATA
neo3vm-0.10.1.dist-info/WHEEL
neo3vm-0.10.1.dist-info/top_level.txt
neo3vm-0.10.1.dist-info/RECORD
