Metadata-Version: 2.1
Name: neo3vm
Version: 0.10.1
Summary: C++ port of the NEO 3 Blockchain virtual machine
Home-page: https://github.com/CityOfZion/neo3vm
Author: Erik van den Brink
Author-email: erik@coz.io
License: MIT
Platform: UNKNOWN
Classifier: Development Status :: 4 - Beta
Classifier: Intended Audience :: Developers
Classifier: License :: OSI Approved :: MIT License
Classifier: Programming Language :: Python :: 3.8
Classifier: Programming Language :: Python :: 3.9
Classifier: Programming Language :: C++
Requires-Dist: pybiginteger
